writeprints_static/__init__.py
writeprints_static/base.py
writeprints_static/lexical_features.py
writeprints_static/syntactic_features.py
writeprints_static-0.0.2.dist-info/LICENSE
writeprints_static-0.0.2.dist-info/WHEEL
writeprints_static-0.0.2.dist-info/METADATA
writeprints_static-0.0.2.dist-info/RECORD
