Metadata-Version: 2.1
Name: writeprints-static
Version: 0.0.2
Summary: Extract lexical and syntactic features for authorship attribution research.
Home-page: https://github.com/literary-materials/writeprints-static
License: ISC
Author: writeprints-static Authors
Requires-Python: >=3.8,<4.0
Classifier: License :: OSI Approved
Classifier: Programming Language :: Python :: 3
Classifier: Programming Language :: Python :: 3.10
Classifier: Programming Language :: Python :: 3.8
Classifier: Programming Language :: Python :: 3.9
Requires-Dist: numpy (>=1.0.0,<2.0.0)
Requires-Dist: scipy (>=1.5.0,<2.0.0)
Requires-Dist: spacy (==3.0.8)
Project-URL: Repository, https://github.com/literary-materials/writeprints-static
